altadata/__init__.py
altadata/altadata.py
altadata-0.2.0.dist-info/LICENSE
altadata-0.2.0.dist-info/METADATA
altadata-0.2.0.dist-info/WHEEL
altadata-0.2.0.dist-info/top_level.txt
altadata-0.2.0.dist-info/RECORD
