Metadata-Version: 2.1
Name: altadata
Version: 0.2.0
Summary: Python library for the ALTADATA API
Home-page: https://github.com/altabering/altadata-python
Author: ALTADATA
Author-email: contact@altadata.io
License: MIT
Keywords: altadata api data marketplace
Platform: UNKNOWN
Classifier: Intended Audience :: Developers
Classifier: License :: OSI Approved :: MIT License
Classifier: Topic :: Software Development
Classifier: Operating System :: OS Independent
Classifier: Programming Language :: Python :: 3.5
Classifier: Programming Language :: Python :: 3.6
Classifier: Programming Language :: Python :: 3.7
Classifier: Programming Language :: Python :: 3.8
Classifier: Programming Language :: Python :: 3.9
Requires-Python: >= 3.5
Requires-Dist: requests (>=2.7.0)
Provides-Extra: dataframe_functionality
Requires-Dist: pandas (>=0.25.3) ; extra == 'dataframe_functionality'
